infra_3drc/__init__.py
infra_3drc/class_names.py
infra_3drc/frame.py
infra_3drc/Infra3DRC.py
infra_3drc/utils.py
infra_3drc-1.0.2.dist-info/METADATA
infra_3drc-1.0.2.dist-info/WHEEL
infra_3drc-1.0.2.dist-info/RECORD
