Metadata-Version: 2.1
Name: infra-3drc
Version: 1.0.2
Summary: This is the SDK to extract and perform various operations using INFRA-3DRC public dataset
Home-page: https://github.com/FraunhoferIVI/INFRA-3DRC-Dataset
Author: Shiva Agrawal
Author-email: shiva.agrawal@thi.de
Requires-Python: >=3.8,<3.11
Classifier: Programming Language :: Python :: 3
Classifier: Programming Language :: Python :: 3.8
Classifier: Programming Language :: Python :: 3.9
Classifier: Programming Language :: Python :: 3.10
Requires-Dist: matplotlib (==3.4.3)
Requires-Dist: numpy (>=1.19.0)
Requires-Dist: opencv-contrib-python (==4.5.5.64)
Requires-Dist: opencv-python (==4.6.0.66)
Project-URL: Repository, https://github.com/FraunhoferIVI/INFRA-3DRC-Dataset
